{"nodes": [{"id": "app_models_sales_resource_py", "label": "sales_resource.py", "file_type": "code", "source_file": "app\\models\\sales_resource.py", "source_location": "L1"}, {"id": "sales_resource_salesresource", "label": "SalesResource", "file_type": "code", "source_file": "app\\models\\sales_resource.py", "source_location": "L18"}, {"id": "sqlmodel", "label": "SQLModel", "file_type": "code", "source_file": "", "source_location": ""}, {"id": "sales_resource_salesresourcecreate", "label": "SalesResourceCreate", "file_type": "code", "source_file": "app\\models\\sales_resource.py", "source_location": "L49"}, {"id": "basemodel", "label": "BaseModel", "file_type": "code", "source_file": "", "source_location": ""}, {"id": "sales_resource_salesresourceread", "label": "SalesResourceRead", "file_type": "code", "source_file": "app\\models\\sales_resource.py", "source_location": "L58"}, {"id": "sales_resource_salesresourceupdate", "label": "SalesResourceUpdate", "file_type": "code", "source_file": "app\\models\\sales_resource.py", "source_location": "L75"}, {"id": "sales_resource_rationale_1", "label": "Sales Knowledge Base \u2014 uploadable resources (ROI templates, case studies, compet", "file_type": "rationale", "source_file": "app\\models\\sales_resource.py", "source_location": "L1"}], "edges": [{"source": "app_models_sales_resource_py", "target": "datetime", "relation": "imports_from", "confidence": "EXTRACTED", "source_file": "app\\models\\sales_resource.py", "source_location": "L8", "weight": 1.0}, {"source": "app_models_sales_resource_py", "target": "typing", "relation": "imports_from", "confidence": "EXTRACTED", "source_file": "app\\models\\sales_resource.py", "source_location": "L9", "weight": 1.0}, {"source": "app_models_sales_resource_py", "target": "uuid", "relation": "imports_from", "confidence": "EXTRACTED", "source_file": "app\\models\\sales_resource.py", "source_location": "L10", "weight": 1.0}, {"source": "app_models_sales_resource_py", "target": "pydantic", "relation": "imports_from", "confidence": "EXTRACTED", "source_file": "app\\models\\sales_resource.py", "source_location": "L12", "weight": 1.0}, {"source": "app_models_sales_resource_py", "target": "sqlalchemy", "relation": "imports_from", "confidence": "EXTRACTED", "source_file": "app\\models\\sales_resource.py", "source_location": "L13", "weight": 1.0}, {"source": "app_models_sales_resource_py", "target": "sqlalchemy_dialects_postgresql", "relation": "imports_from", "confidence": "EXTRACTED", "source_file": "app\\models\\sales_resource.py", "source_location": "L14", "weight": 1.0}, {"source": "app_models_sales_resource_py", "target": "sqlmodel", "relation": "imports_from", "confidence": "EXTRACTED", "source_file": "app\\models\\sales_resource.py", "source_location": "L15", "weight": 1.0}, {"source": "app_models_sales_resource_py", "target": "sales_resource_salesresource", "relation": "contains", "confidence": "EXTRACTED", "source_file": "app\\models\\sales_resource.py", "source_location": "L18", "weight": 1.0}, {"source": "sales_resource_salesresource", "target": "sqlmodel", "relation": "inherits", "confidence": "EXTRACTED", "source_file": "app\\models\\sales_resource.py", "source_location": "L18", "weight": 1.0}, {"source": "app_models_sales_resource_py", "target": "sales_resource_salesresourcecreate", "relation": "contains", "confidence": "EXTRACTED", "source_file": "app\\models\\sales_resource.py", "source_location": "L49", "weight": 1.0}, {"source": "sales_resource_salesresourcecreate", "target": "basemodel", "relation": "inherits", "confidence": "EXTRACTED", "source_file": "app\\models\\sales_resource.py", "source_location": "L49", "weight": 1.0}, {"source": "app_models_sales_resource_py", "target": "sales_resource_salesresourceread", "relation": "contains", "confidence": "EXTRACTED", "source_file": "app\\models\\sales_resource.py", "source_location": "L58", "weight": 1.0}, {"source": "sales_resource_salesresourceread", "target": "basemodel", "relation": "inherits", "confidence": "EXTRACTED", "source_file": "app\\models\\sales_resource.py", "source_location": "L58", "weight": 1.0}, {"source": "app_models_sales_resource_py", "target": "sales_resource_salesresourceupdate", "relation": "contains", "confidence": "EXTRACTED", "source_file": "app\\models\\sales_resource.py", "source_location": "L75", "weight": 1.0}, {"source": "sales_resource_salesresourceupdate", "target": "basemodel", "relation": "inherits", "confidence": "EXTRACTED", "source_file": "app\\models\\sales_resource.py", "source_location": "L75", "weight": 1.0}, {"source": "sales_resource_rationale_1", "target": "app_models_sales_resource_py", "relation": "rationale_for", "confidence": "EXTRACTED", "source_file": "app\\models\\sales_resource.py", "source_location": "L1", "weight": 1.0}]}