{"nodes": [{"id": "frontend_src_components_deal_dealdetaildrawer_tsx", "label": "DealDetailDrawer.tsx", "file_type": "code", "source_file": "frontend\\src\\components\\deal\\DealDetailDrawer.tsx", "source_location": "L1"}, {"id": "dealdetaildrawer_engagementtone", "label": "engagementTone()", "file_type": "code", "source_file": "frontend\\src\\components\\deal\\DealDetailDrawer.tsx", "source_location": "L58"}, {"id": "dealdetaildrawer_engagementstatusjustification", "label": "engagementStatusJustification()", "file_type": "code", "source_file": "frontend\\src\\components\\deal\\DealDetailDrawer.tsx", "source_location": "L73"}, {"id": "dealdetaildrawer_relativetime", "label": "relativeTime()", "file_type": "code", "source_file": "frontend\\src\\components\\deal\\DealDetailDrawer.tsx", "source_location": "L88"}, {"id": "dealdetaildrawer_engagementsummary", "label": "engagementSummary()", "file_type": "code", "source_file": "frontend\\src\\components\\deal\\DealDetailDrawer.tsx", "source_location": "L102"}, {"id": "dealdetaildrawer_engagementpanel", "label": "EngagementPanel()", "file_type": "code", "source_file": "frontend\\src\\components\\deal\\DealDetailDrawer.tsx", "source_location": "L151"}, {"id": "dealdetaildrawer_handleclick", "label": "handleClick()", "file_type": "code", "source_file": "frontend\\src\\components\\deal\\DealDetailDrawer.tsx", "source_location": "L324"}, {"id": "dealdetaildrawer_patchdeal", "label": "patchDeal()", "file_type": "code", "source_file": "frontend\\src\\components\\deal\\DealDetailDrawer.tsx", "source_location": "L408"}, {"id": "dealdetaildrawer_handlemovestage", "label": "handleMoveStage()", "file_type": "code", "source_file": "frontend\\src\\components\\deal\\DealDetailDrawer.tsx", "source_location": "L413"}, {"id": "dealdetaildrawer_handlenamesave", "label": "handleNameSave()", "file_type": "code", "source_file": "frontend\\src\\components\\deal\\DealDetailDrawer.tsx", "source_location": "L421"}, {"id": "dealdetaildrawer_handleaddcomment", "label": "handleAddComment()", "file_type": "code", "source_file": "frontend\\src\\components\\deal\\DealDetailDrawer.tsx", "source_location": "L430"}, {"id": "dealdetaildrawer_handledeletedeal", "label": "handleDeleteDeal()", "file_type": "code", "source_file": "frontend\\src\\components\\deal\\DealDetailDrawer.tsx", "source_location": "L440"}, {"id": "dealdetaildrawer_searchcontacts", "label": "searchContacts()", "file_type": "code", "source_file": "frontend\\src\\components\\deal\\DealDetailDrawer.tsx", "source_location": "L451"}, {"id": "dealdetaildrawer_handlelinkcontact", "label": "handleLinkContact()", "file_type": "code", "source_file": "frontend\\src\\components\\deal\\DealDetailDrawer.tsx", "source_location": "L469"}, {"id": "dealdetaildrawer_handleunlinkcontact", "label": "handleUnlinkContact()", "file_type": "code", "source_file": "frontend\\src\\components\\deal\\DealDetailDrawer.tsx", "source_location": "L478"}, {"id": "dealdetaildrawer_handleaddtag", "label": "handleAddTag()", "file_type": "code", "source_file": "frontend\\src\\components\\deal\\DealDetailDrawer.tsx", "source_location": "L485"}, {"id": "dealdetaildrawer_handleremovetag", "label": "handleRemoveTag()", "file_type": "code", "source_file": "frontend\\src\\components\\deal\\DealDetailDrawer.tsx", "source_location": "L492"}, {"id": "dealdetaildrawer_async", "label": "async()", "file_type": "code", "source_file": "frontend\\src\\components\\deal\\DealDetailDrawer.tsx", "source_location": "L1164"}, {"id": "dealdetaildrawer_handlechange", "label": "handleChange()", "file_type": "code", "source_file": "frontend\\src\\components\\deal\\DealDetailDrawer.tsx", "source_location": "L1387"}], "edges": [{"source": "frontend_src_components_deal_dealdetaildrawer_tsx", "target": "react", "relation": "imports_from", "confidence": "EXTRACTED", "source_file": "frontend\\src\\components\\deal\\DealDetailDrawer.tsx", "source_location": "L1", "weight": 1.0}, {"source": "frontend_src_components_deal_dealdetaildrawer_tsx", "target": "lucide_react", "relation": "imports_from", "confidence": "EXTRACTED", "source_file": "frontend\\src\\components\\deal\\DealDetailDrawer.tsx", "source_location": "L2", "weight": 1.0}, {"source": "frontend_src_components_deal_dealdetaildrawer_tsx", "target": "frontend_src_components_deal_lib_api", "relation": "imports_from", "confidence": "EXTRACTED", "source_file": "frontend\\src\\components\\deal\\DealDetailDrawer.tsx", "source_location": "L7", "weight": 1.0}, {"source": "frontend_src_components_deal_dealdetaildrawer_tsx", "target": "frontend_src_components_deal_lib_api", "relation": "imports_from", "confidence": "EXTRACTED", "source_file": "frontend\\src\\components\\deal\\DealDetailDrawer.tsx", "source_location": "L8", "weight": 1.0}, {"source": "frontend_src_components_deal_dealdetaildrawer_tsx", "target": "frontend_src_components_deal_lib_authcontext", "relation": "imports_from", "confidence": "EXTRACTED", "source_file": "frontend\\src\\components\\deal\\DealDetailDrawer.tsx", "source_location": "L9", "weight": 1.0}, {"source": "frontend_src_components_deal_dealdetaildrawer_tsx", "target": "frontend_src_components_deal_types", "relation": "imports_from", "confidence": "EXTRACTED", "source_file": "frontend\\src\\components\\deal\\DealDetailDrawer.tsx", "source_location": "L10", "weight": 1.0}, {"source": "frontend_src_components_deal_dealdetaildrawer_tsx", "target": "frontend_src_components_deal_lib_utils", "relation": "imports_from", "confidence": "EXTRACTED", "source_file": "frontend\\src\\components\\deal\\DealDetailDrawer.tsx", "source_location": "L11", "weight": 1.0}, {"source": "frontend_src_components_deal_dealdetaildrawer_tsx", "target": "frontend_src_components_deal_tasks_taskcentermodal", "relation": "imports_from", "confidence": "EXTRACTED", "source_file": "frontend\\src\\components\\deal\\DealDetailDrawer.tsx", "source_location": "L12", "weight": 1.0}, {"source": "frontend_src_components_deal_dealdetaildrawer_tsx", "target": "frontend_src_components_deal_activity_transcriptpreview", "relation": "imports_from", "confidence": "EXTRACTED", "source_file": "frontend\\src\\components\\deal\\DealDetailDrawer.tsx", "source_location": "L13", "weight": 1.0}, {"source": "frontend_src_components_deal_dealdetaildrawer_tsx", "target": "dealdetaildrawer_engagementtone", "relation": "contains", "confidence": "EXTRACTED", "source_file": "frontend\\src\\components\\deal\\DealDetailDrawer.tsx", "source_location": "L58", "weight": 1.0}, {"source": "frontend_src_components_deal_dealdetaildrawer_tsx", "target": "dealdetaildrawer_engagementstatusjustification", "relation": "contains", "confidence": "EXTRACTED", "source_file": "frontend\\src\\components\\deal\\DealDetailDrawer.tsx", "source_location": "L73", "weight": 1.0}, {"source": "frontend_src_components_deal_dealdetaildrawer_tsx", "target": "dealdetaildrawer_relativetime", "relation": "contains", "confidence": "EXTRACTED", "source_file": "frontend\\src\\components\\deal\\DealDetailDrawer.tsx", "source_location": "L88", "weight": 1.0}, {"source": "frontend_src_components_deal_dealdetaildrawer_tsx", "target": "dealdetaildrawer_engagementsummary", "relation": "contains", "confidence": "EXTRACTED", "source_file": "frontend\\src\\components\\deal\\DealDetailDrawer.tsx", "source_location": "L102", "weight": 1.0}, {"source": "frontend_src_components_deal_dealdetaildrawer_tsx", "target": "dealdetaildrawer_engagementpanel", "relation": "contains", "confidence": "EXTRACTED", "source_file": "frontend\\src\\components\\deal\\DealDetailDrawer.tsx", "source_location": "L151", "weight": 1.0}, {"source": "frontend_src_components_deal_dealdetaildrawer_tsx", "target": "dealdetaildrawer_handleclick", "relation": "contains", "confidence": "EXTRACTED", "source_file": "frontend\\src\\components\\deal\\DealDetailDrawer.tsx", "source_location": "L324", "weight": 1.0}, {"source": "frontend_src_components_deal_dealdetaildrawer_tsx", "target": "dealdetaildrawer_patchdeal", "relation": "contains", "confidence": "EXTRACTED", "source_file": "frontend\\src\\components\\deal\\DealDetailDrawer.tsx", "source_location": "L408", "weight": 1.0}, {"source": "frontend_src_components_deal_dealdetaildrawer_tsx", "target": "dealdetaildrawer_handlemovestage", "relation": "contains", "confidence": "EXTRACTED", "source_file": "frontend\\src\\components\\deal\\DealDetailDrawer.tsx", "source_location": "L413", "weight": 1.0}, {"source": "frontend_src_components_deal_dealdetaildrawer_tsx", "target": "dealdetaildrawer_handlenamesave", "relation": "contains", "confidence": "EXTRACTED", "source_file": "frontend\\src\\components\\deal\\DealDetailDrawer.tsx", "source_location": "L421", "weight": 1.0}, {"source": "frontend_src_components_deal_dealdetaildrawer_tsx", "target": "dealdetaildrawer_handleaddcomment", "relation": "contains", "confidence": "EXTRACTED", "source_file": "frontend\\src\\components\\deal\\DealDetailDrawer.tsx", "source_location": "L430", "weight": 1.0}, {"source": "frontend_src_components_deal_dealdetaildrawer_tsx", "target": "dealdetaildrawer_handledeletedeal", "relation": "contains", "confidence": "EXTRACTED", "source_file": "frontend\\src\\components\\deal\\DealDetailDrawer.tsx", "source_location": "L440", "weight": 1.0}, {"source": "frontend_src_components_deal_dealdetaildrawer_tsx", "target": "dealdetaildrawer_searchcontacts", "relation": "contains", "confidence": "EXTRACTED", "source_file": "frontend\\src\\components\\deal\\DealDetailDrawer.tsx", "source_location": "L451", "weight": 1.0}, {"source": "frontend_src_components_deal_dealdetaildrawer_tsx", "target": "dealdetaildrawer_handlelinkcontact", "relation": "contains", "confidence": "EXTRACTED", "source_file": "frontend\\src\\components\\deal\\DealDetailDrawer.tsx", "source_location": "L469", "weight": 1.0}, {"source": "frontend_src_components_deal_dealdetaildrawer_tsx", "target": "dealdetaildrawer_handleunlinkcontact", "relation": "contains", "confidence": "EXTRACTED", "source_file": "frontend\\src\\components\\deal\\DealDetailDrawer.tsx", "source_location": "L478", "weight": 1.0}, {"source": "frontend_src_components_deal_dealdetaildrawer_tsx", "target": "dealdetaildrawer_handleaddtag", "relation": "contains", "confidence": "EXTRACTED", "source_file": "frontend\\src\\components\\deal\\DealDetailDrawer.tsx", "source_location": "L485", "weight": 1.0}, {"source": "frontend_src_components_deal_dealdetaildrawer_tsx", "target": "dealdetaildrawer_handleremovetag", "relation": "contains", "confidence": "EXTRACTED", "source_file": "frontend\\src\\components\\deal\\DealDetailDrawer.tsx", "source_location": "L492", "weight": 1.0}, {"source": "frontend_src_components_deal_dealdetaildrawer_tsx", "target": "dealdetaildrawer_async", "relation": "contains", "confidence": "EXTRACTED", "source_file": "frontend\\src\\components\\deal\\DealDetailDrawer.tsx", "source_location": "L1164", "weight": 1.0}, {"source": "frontend_src_components_deal_dealdetaildrawer_tsx", "target": "dealdetaildrawer_async", "relation": "contains", "confidence": "EXTRACTED", "source_file": "frontend\\src\\components\\deal\\DealDetailDrawer.tsx", "source_location": "L1174", "weight": 1.0}, {"source": "frontend_src_components_deal_dealdetaildrawer_tsx", "target": "dealdetaildrawer_handlechange", "relation": "contains", "confidence": "EXTRACTED", "source_file": "frontend\\src\\components\\deal\\DealDetailDrawer.tsx", "source_location": "L1387", "weight": 1.0}, {"source": "dealdetaildrawer_engagementpanel", "target": "dealdetaildrawer_engagementtone", "relation": "calls", "confidence": "EXTRACTED", "source_file": "frontend\\src\\components\\deal\\DealDetailDrawer.tsx", "source_location": "L163", "weight": 1.0}, {"source": "dealdetaildrawer_engagementpanel", "target": "dealdetaildrawer_engagementsummary", "relation": "calls", "confidence": "EXTRACTED", "source_file": "frontend\\src\\components\\deal\\DealDetailDrawer.tsx", "source_location": "L164", "weight": 1.0}, {"source": "dealdetaildrawer_engagementpanel", "target": "dealdetaildrawer_engagementstatusjustification", "relation": "calls", "confidence": "EXTRACTED", "source_file": "frontend\\src\\components\\deal\\DealDetailDrawer.tsx", "source_location": "L169", "weight": 1.0}, {"source": "dealdetaildrawer_engagementpanel", "target": "dealdetaildrawer_relativetime", "relation": "calls", "confidence": "EXTRACTED", "source_file": "frontend\\src\\components\\deal\\DealDetailDrawer.tsx", "source_location": "L170", "weight": 1.0}, {"source": "dealdetaildrawer_handlenamesave", "target": "dealdetaildrawer_patchdeal", "relation": "calls", "confidence": "EXTRACTED", "source_file": "frontend\\src\\components\\deal\\DealDetailDrawer.tsx", "source_location": "L424", "weight": 1.0}, {"source": "dealdetaildrawer_handleaddtag", "target": "dealdetaildrawer_patchdeal", "relation": "calls", "confidence": "EXTRACTED", "source_file": "frontend\\src\\components\\deal\\DealDetailDrawer.tsx", "source_location": "L488", "weight": 1.0}, {"source": "dealdetaildrawer_handleremovetag", "target": "dealdetaildrawer_patchdeal", "relation": "calls", "confidence": "EXTRACTED", "source_file": "frontend\\src\\components\\deal\\DealDetailDrawer.tsx", "source_location": "L493", "weight": 1.0}, {"source": "dealdetaildrawer_async", "target": "dealdetaildrawer_patchdeal", "relation": "calls", "confidence": "EXTRACTED", "source_file": "frontend\\src\\components\\deal\\DealDetailDrawer.tsx", "source_location": "L1176", "weight": 1.0}]}