{"nodes": [{"id": "app_clients_google_calendar_py", "label": "google_calendar.py", "file_type": "code", "source_file": "app\\clients\\google_calendar.py", "source_location": "L1"}, {"id": "google_calendar_calendarevent", "label": "CalendarEvent", "file_type": "code", "source_file": "app\\clients\\google_calendar.py", "source_location": "L31"}, {"id": "google_calendar_refresh_token_if_needed", "label": "_refresh_token_if_needed()", "file_type": "code", "source_file": "app\\clients\\google_calendar.py", "source_location": "L44"}, {"id": "google_calendar_parse_event", "label": "_parse_event()", "file_type": "code", "source_file": "app\\clients\\google_calendar.py", "source_location": "L83"}, {"id": "google_calendar_fetch_upcoming_events", "label": "fetch_upcoming_events()", "file_type": "code", "source_file": "app\\clients\\google_calendar.py", "source_location": "L146"}, {"id": "google_calendar_rationale_1", "label": "Google Calendar client \u2014 fetches upcoming events for a connected personal accoun", "file_type": "rationale", "source_file": "app\\clients\\google_calendar.py", "source_location": "L1"}, {"id": "google_calendar_rationale_32", "label": "Parsed Google Calendar event.", "file_type": "rationale", "source_file": "app\\clients\\google_calendar.py", "source_location": "L32"}, {"id": "google_calendar_rationale_45", "label": "Refresh the access token if expired. Returns updated token_data.", "file_type": "rationale", "source_file": "app\\clients\\google_calendar.py", "source_location": "L45"}, {"id": "google_calendar_rationale_84", "label": "Parse a raw Google Calendar event dict into a CalendarEvent.", "file_type": "rationale", "source_file": "app\\clients\\google_calendar.py", "source_location": "L84"}, {"id": "google_calendar_rationale_153", "label": "Fetch upcoming calendar events for the connected account.      Returns (events,", "file_type": "rationale", "source_file": "app\\clients\\google_calendar.py", "source_location": "L153"}], "edges": [{"source": "app_clients_google_calendar_py", "target": "logging", "relation": "imports", "confidence": "EXTRACTED", "source_file": "app\\clients\\google_calendar.py", "source_location": "L15", "weight": 1.0}, {"source": "app_clients_google_calendar_py", "target": "dataclasses", "relation": "imports_from", "confidence": "EXTRACTED", "source_file": "app\\clients\\google_calendar.py", "source_location": "L16", "weight": 1.0}, {"source": "app_clients_google_calendar_py", "target": "datetime", "relation": "imports_from", "confidence": "EXTRACTED", "source_file": "app\\clients\\google_calendar.py", "source_location": "L17", "weight": 1.0}, {"source": "app_clients_google_calendar_py", "target": "typing", "relation": "imports_from", "confidence": "EXTRACTED", "source_file": "app\\clients\\google_calendar.py", "source_location": "L18", "weight": 1.0}, {"source": "app_clients_google_calendar_py", "target": "httpx", "relation": "imports", "confidence": "EXTRACTED", "source_file": "app\\clients\\google_calendar.py", "source_location": "L20", "weight": 1.0}, {"source": "app_clients_google_calendar_py", "target": "app_services_gmail_oauth", "relation": "imports_from", "confidence": "EXTRACTED", "source_file": "app\\clients\\google_calendar.py", "source_location": "L22", "weight": 1.0}, {"source": "app_clients_google_calendar_py", "target": "google_calendar_calendarevent", "relation": "contains", "confidence": "EXTRACTED", "source_file": "app\\clients\\google_calendar.py", "source_location": "L31", "weight": 1.0}, {"source": "app_clients_google_calendar_py", "target": "google_calendar_refresh_token_if_needed", "relation": "contains", "confidence": "EXTRACTED", "source_file": "app\\clients\\google_calendar.py", "source_location": "L44", "weight": 1.0}, {"source": "app_clients_google_calendar_py", "target": "google_calendar_parse_event", "relation": "contains", "confidence": "EXTRACTED", "source_file": "app\\clients\\google_calendar.py", "source_location": "L83", "weight": 1.0}, {"source": "app_clients_google_calendar_py", "target": "google_calendar_fetch_upcoming_events", "relation": "contains", "confidence": "EXTRACTED", "source_file": "app\\clients\\google_calendar.py", "source_location": "L146", "weight": 1.0}, {"source": "google_calendar_parse_event", "target": "google_calendar_calendarevent", "relation": "calls", "confidence": "EXTRACTED", "source_file": "app\\clients\\google_calendar.py", "source_location": "L133", "weight": 1.0}, {"source": "google_calendar_fetch_upcoming_events", "target": "google_calendar_refresh_token_if_needed", "relation": "calls", "confidence": "EXTRACTED", "source_file": "app\\clients\\google_calendar.py", "source_location": "L173", "weight": 1.0}, {"source": "google_calendar_fetch_upcoming_events", "target": "google_calendar_parse_event", "relation": "calls", "confidence": "EXTRACTED", "source_file": "app\\clients\\google_calendar.py", "source_location": "L209", "weight": 1.0}, {"source": "google_calendar_rationale_1", "target": "app_clients_google_calendar_py", "relation": "rationale_for", "confidence": "EXTRACTED", "source_file": "app\\clients\\google_calendar.py", "source_location": "L1", "weight": 1.0}, {"source": "google_calendar_rationale_32", "target": "google_calendar_calendarevent", "relation": "rationale_for", "confidence": "EXTRACTED", "source_file": "app\\clients\\google_calendar.py", "source_location": "L32", "weight": 1.0}, {"source": "google_calendar_rationale_45", "target": "google_calendar_refresh_token_if_needed", "relation": "rationale_for", "confidence": "EXTRACTED", "source_file": "app\\clients\\google_calendar.py", "source_location": "L45", "weight": 1.0}, {"source": "google_calendar_rationale_84", "target": "google_calendar_parse_event", "relation": "rationale_for", "confidence": "EXTRACTED", "source_file": "app\\clients\\google_calendar.py", "source_location": "L84", "weight": 1.0}, {"source": "google_calendar_rationale_153", "target": "google_calendar_fetch_upcoming_events", "relation": "rationale_for", "confidence": "EXTRACTED", "source_file": "app\\clients\\google_calendar.py", "source_location": "L153", "weight": 1.0}]}